{
  "unversionedId": "sess3",
  "id": "sess3",
  "isDocsHomePage": false,
  "title": "Bibliotecas Utilizadas",
  "description": "Neste tópico falaremos sobre as bibliotecas importadas no projeto e para que elas estão sendo utilizadas.",
  "source": "@site/docs/sess3.md",
  "permalink": "/docs/sess3",
  "editUrl": "https://github.com/facebook/docusaurus/edit/master/website/docs/sess3.md",
  "sidebar": "someSidebar",
  "previous": {
    "title": "Hierarquia de pastas",
    "permalink": "/docs/sess2"
  },
  "next": {
    "title": "Componentes",
    "permalink": "/docs/sess4"
  }
}